_pyOrbfit.cpython-39-darwin.so
libspacerocks.cpython-39-darwin.so
spacerocks/__init__.py
spacerocks/cbindings.py
spacerocks/constants.py
spacerocks/convenience.py
spacerocks/downloader.py
spacerocks/ephemerides.py
spacerocks/keplerorbit.py
spacerocks/model.py
spacerocks/mpchecker.py
spacerocks/observer.py
spacerocks/orbfit.py
spacerocks/orbitsppmasses.py
spacerocks/paths.py
spacerocks/prediction.py
spacerocks/pyOrbfit.py
spacerocks/simulation.py
spacerocks/spacerock.py
spacerocks/spice.py
spacerocks/units.py
spacerocks/utils.py
spacerocks/vector.py
spacerocks/data/observatories.csv
spacerocks/data/pyOrbfit/binEphem.423
spacerocks/data/pyOrbfit/observatories.dat
spacerocks-2.1.22.data/data/AllMPC.c
spacerocks-2.1.22.data/data/abg_to_aei.c
spacerocks-2.1.22.data/data/abg_to_xyz.c
spacerocks-2.1.22.data/data/aeiderivs.c
spacerocks-2.1.22.data/data/binEphem.423
spacerocks-2.1.22.data/data/covsrt.c
spacerocks-2.1.22.data/data/dms.c
spacerocks-2.1.22.data/data/ephem_earth.c
spacerocks-2.1.22.data/data/ephem_read.h
spacerocks-2.1.22.data/data/ephem_types.h
spacerocks-2.1.22.data/data/fit_radec.c
spacerocks-2.1.22.data/data/gasdev.c
spacerocks-2.1.22.data/data/gaussj.c
spacerocks-2.1.22.data/data/hststuff1.c
spacerocks-2.1.22.data/data/hststuff2.c
spacerocks-2.1.22.data/data/hststuff3.c
spacerocks-2.1.22.data/data/hststuff4.c
spacerocks-2.1.22.data/data/lubksb.c
spacerocks-2.1.22.data/data/ludcmp.c
spacerocks-2.1.22.data/data/mrqcof_orbit.c
spacerocks-2.1.22.data/data/mrqmin_orbit.c
spacerocks-2.1.22.data/data/nrutil.c
spacerocks-2.1.22.data/data/nrutil.h
spacerocks-2.1.22.data/data/numpy.i
spacerocks-2.1.22.data/data/observatories.csv
spacerocks-2.1.22.data/data/observatories.dat
spacerocks-2.1.22.data/data/orbfit.h
spacerocks-2.1.22.data/data/orbfit1.c
spacerocks-2.1.22.data/data/orbfit2.c
spacerocks-2.1.22.data/data/planner.c
spacerocks-2.1.22.data/data/postdict.c
spacerocks-2.1.22.data/data/predict.c
spacerocks-2.1.22.data/data/pyOrbfit.i
spacerocks-2.1.22.dist-info/LICENSE.md
spacerocks-2.1.22.dist-info/METADATA
spacerocks-2.1.22.dist-info/WHEEL
spacerocks-2.1.22.dist-info/top_level.txt
spacerocks-2.1.22.dist-info/RECORD
